vecha/__init__.py
vecha/chain.py
vecha/contract.py
vecha/function.py
vecha/request/__init__.py
vecha/request/request.py
vecha/request/typs.py
vecha/vemodel/__init__.py
vecha/vemodel/event.py
vecha/vemodel/function.py
vecha/vemodel/transaction.py
vecha/vemodel/translator.py
vecha/vemodel/utils.py
vecha-0.0.1.dist-info/LICENSE
vecha-0.0.1.dist-info/METADATA
vecha-0.0.1.dist-info/WHEEL
vecha-0.0.1.dist-info/entry_points.txt
vecha-0.0.1.dist-info/top_level.txt
vecha-0.0.1.dist-info/RECORD
