Metadata-Version: 2.1
Name: vecha
Version: 0.0.1
Summary: Python library to aid DApp-Server development on VeChain Thor.
Home-page: https://github.com/uldaman/vecha.py
Author: Han Xiao
Author-email: smallcpp@foxmail.com
License: MIT
Keywords: thor blockchain ethereum
Platform: UNKNOWN
Classifier: Intended Audience :: Developers
Classifier: Programming Language :: Python :: 3.6
Requires-Python: >=3.6
Requires-Dist: eth-keys (==0.2.1)
Requires-Dist: json-rpc (==1.12.1)
Requires-Dist: lru-dict (==1.1.6)
Requires-Dist: requests (==2.21.0)
Requires-Dist: rlp (==0.6.0)
